{
  "__inputs": [
    {
      "name": "DS_ZABBIX",
      "label": "Zabbix",
      "description": "",
      "type": "datasource",
      "pluginId": "alexanderzobnin-zabbix-datasource",
      "pluginName": "Zabbix"
    }
  ],
  "__elements": {},
  "__requires": [
    {
      "type": "datasource",
      "id": "alexanderzobnin-zabbix-datasource",
      "name": "Zabbix",
      "version": "1.0.0"
    },
    {
      "type": "grafana",
      "id": "grafana",
      "name": "Grafana",
      "version": "9.1.0"
    },
    {
      "type": "panel",
      "id": "stat",
      "name": "Stat",
      "version": ""
    },
    {
      "type": "panel",
      "id": "table",
      "name": "Table",
      "version": ""
    },
    {
      "type": "panel",
      "id": "timeseries",
      "name": "Time series",
      "version": ""
    }
  ],
  "annotations": {
    "list": [
      {
        "builtIn": 1,
        "datasource": {
          "type": "datasource",
          "uid": "grafana"
        },
        "enable": true,
        "hide": true,
        "iconColor": "rgba(0, 211, 255, 1)",
        "name": "Annotations & Alerts",
        "target": {
          "limit": 100,
          "matchAny": false,
          "tags": [],
          "type": "dashboard"
        },
        "type": "dashboard"
      }
    ]
  },
  "description": "",
  "editable": true,
  "fiscalYearStartMonth": 0,
  "gnetId": 5363,
  "graphTooltip": 1,
  "id": null,
  "links": [],
  "liveNow": false,
  "panels": [
    {
      "gridPos": {
        "h": 1,
        "w": 24,
        "x": 0,
        "y": 0
      },
      "id": 104,
      "title": "ray-hapve",
      "type": "row"
    },
    {
      "datasource": {
        "type": "alexanderzobnin-zabbix-datasource",
        "uid": "${DS_ZABBIX}"
      },
      "fieldConfig": {
        "defaults": {
          "color": {
            "mode": "thresholds"
          },
          "mappings": [],
          "thresholds": {
            "mode": "absolute",
            "steps": [
              {
                "color": "green",
                "value": null
              }
            ]
          }
        },
        "overrides": []
      },
      "gridPos": {
        "h": 3,
        "w": 6,
        "x": 0,
        "y": 1
      },
      "id": 110,
      "options": {
        "colorMode": "value",
        "graphMode": "none",
        "justifyMode": "center",
        "orientation": "auto",
        "reduceOptions": {
          "calcs": [
            "max"
          ],
          "fields": "",
          "values": false
        },
        "textMode": "value_and_name"
      },
      "pluginVersion": "9.1.0",
      "targets": [
        {
          "application": {
            "filter": ""
          },
          "countTriggersBy": "",
          "datasource": {
            "type": "alexanderzobnin-zabbix-datasource",
            "uid": "${DS_ZABBIX}"
          },
          "functions": [],
          "group": {
            "filter": "HomeServer/pysical-host"
          },
          "hide": false,
          "host": {
            "filter": "/ray-hapve0.*/"
          },
          "item": {
            "filter": "/Number of (CPUs|cores)/"
          },
          "itemTag": {
            "filter": ""
          },
          "macro": {
            "filter": ""
          },
          "options": {
            "count": false,
            "disableDataAlignment": false,
            "showDisabledItems": false,
            "skipEmptyValues": false,
            "useTrends": "default",
            "useZabbixValueMapping": false
          },
          "proxy": {
            "filter": ""
          },
          "queryType": "0",
          "refId": "A",
          "resultFormat": "time_series",
          "schema": 12,
          "table": {
            "skipEmptyValues": false
          },
          "tags": {
            "filter": ""
          },
          "textFilter": "",
          "trigger": {
            "filter": ""
          }
        }
      ],
      "title": "Total CPUs",
      "transformations": [
        {
          "id": "calculateField",
          "options": {
            "alias": " ",
            "mode": "reduceRow",
            "reduce": {
              "include": [
                "ray-hapve01: Number of CPUs",
                "ray-hapve02: Number of CPUs",
                "ray-hapve03: Number of CPUs",
                "ray-hapve04: Number of CPUs"
              ],
              "reducer": "sum"
            },
            "replaceFields": true
          }
        }
      ],
      "type": "stat"
    },
    {
      "datasource": {
        "type": "alexanderzobnin-zabbix-datasource",
        "uid": "${DS_ZABBIX}"
      },
      "fieldConfig": {
        "defaults": {
          "color": {
            "mode": "thresholds"
          },
          "mappings": [],
          "thresholds": {
            "mode": "absolute",
            "steps": [
              {
                "color": "green",
                "value": null
              }
            ]
          },
          "unit": "bytes"
        },
        "overrides": []
      },
      "gridPos": {
        "h": 3,
        "w": 6,
        "x": 6,
        "y": 1
      },
      "id": 107,
      "options": {
        "colorMode": "value",
        "graphMode": "none",
        "justifyMode": "center",
        "orientation": "auto",
        "reduceOptions": {
          "calcs": [
            "max"
          ],
          "fields": "",
          "values": false
        },
        "textMode": "value_and_name"
      },
      "pluginVersion": "9.1.0",
      "targets": [
        {
          "application": {
            "filter": ""
          },
          "countTriggersBy": "",
          "datasource": {
            "type": "alexanderzobnin-zabbix-datasource",
            "uid": "${DS_ZABBIX}"
          },
          "functions": [],
          "group": {
            "filter": "HomeServer/pysical-host"
          },
          "host": {
            "filter": "/ray-hapve0.*/"
          },
          "item": {
            "filter": "Total memory"
          },
          "itemTag": {
            "filter": ""
          },
          "macro": {
            "filter": ""
          },
          "options": {
            "count": false,
            "disableDataAlignment": false,
            "showDisabledItems": false,
            "skipEmptyValues": false,
            "useTrends": "default",
            "useZabbixValueMapping": false
          },
          "proxy": {
            "filter": ""
          },
          "queryType": "0",
          "refId": "A",
          "resultFormat": "time_series",
          "schema": 12,
          "table": {
            "skipEmptyValues": false
          },
          "tags": {
            "filter": ""
          },
          "textFilter": "",
          "trigger": {
            "filter": ""
          }
        }
      ],
      "title": "Total memory",
      "transformations": [
        {
          "id": "calculateField",
          "options": {
            "alias": " ",
            "mode": "reduceRow",
            "reduce": {
              "include": [
                "ray-hapve01: Total memory",
                "ray-hapve02: Total memory",
                "ray-hapve03: Total memory",
                "ray-hapve04: Total memory"
              ],
              "reducer": "sum"
            },
            "replaceFields": true
          }
        }
      ],
      "type": "stat"
    },
    {
      "datasource": {
        "type": "alexanderzobnin-zabbix-datasource",
        "uid": "${DS_ZABBIX}"
      },
      "fieldConfig": {
        "defaults": {
          "color": {
            "mode": "thresholds"
          },
          "mappings": [],
          "thresholds": {
            "mode": "absolute",
            "steps": [
              {
                "color": "green",
                "value": null
              }
            ]
          },
          "unit": "bytes"
        },
        "overrides": []
      },
      "gridPos": {
        "h": 3,
        "w": 6,
        "x": 12,
        "y": 1
      },
      "id": 111,
      "options": {
        "colorMode": "value",
        "graphMode": "none",
        "justifyMode": "center",
        "orientation": "horizontal",
        "reduceOptions": {
          "calcs": [
            "max"
          ],
          "fields": "/^ray\\-hapve01: Proxmox: Storage \\[ray\\-hapve01/synology\\-haproxmox\\]: Size$/",
          "values": false
        },
        "textMode": "value"
      },
      "pluginVersion": "9.1.0",
      "targets": [
        {
          "application": {
            "filter": ""
          },
          "countTriggersBy": "",
          "datasource": {
            "type": "alexanderzobnin-zabbix-datasource",
            "uid": "${DS_ZABBIX}"
          },
          "functions": [],
          "group": {
            "filter": "HomeServer/pysical-host"
          },
          "host": {
            "filter": "/ray-hapve0.*/"
          },
          "item": {
            "filter": "Proxmox: Storage [ray-hapve01/synology-haproxmox]: Size"
          },
          "itemTag": {
            "filter": ""
          },
          "macro": {
            "filter": ""
          },
          "options": {
            "count": false,
            "disableDataAlignment": false,
            "showDisabledItems": false,
            "skipEmptyValues": false,
            "useTrends": "default",
            "useZabbixValueMapping": false
          },
          "proxy": {
            "filter": ""
          },
          "queryType": "0",
          "refId": "A",
          "resultFormat": "time_series",
          "schema": 12,
          "table": {
            "skipEmptyValues": false
          },
          "tags": {
            "filter": ""
          },
          "textFilter": "",
          "trigger": {
            "filter": ""
          }
        }
      ],
      "title": "Synology Storage",
      "transformations": [],
      "type": "stat"
    },
    {
      "datasource": {
        "type": "alexanderzobnin-zabbix-datasource",
        "uid": "${DS_ZABBIX}"
      },
      "fieldConfig": {
        "defaults": {
          "color": {
            "mode": "thresholds"
          },
          "mappings": [],
          "thresholds": {
            "mode": "absolute",
            "steps": [
              {
                "color": "green",
                "value": null
              }
            ]
          },
          "unit": "bytes"
        },
        "overrides": []
      },
      "gridPos": {
        "h": 3,
        "w": 6,
        "x": 18,
        "y": 1
      },
      "id": 112,
      "options": {
        "colorMode": "value",
        "graphMode": "none",
        "justifyMode": "center",
        "orientation": "horizontal",
        "reduceOptions": {
          "calcs": [
            "max"
          ],
          "fields": "",
          "values": false
        },
        "textMode": "value"
      },
      "pluginVersion": "9.1.0",
      "targets": [
        {
          "application": {
            "filter": ""
          },
          "countTriggersBy": "",
          "datasource": {
            "type": "alexanderzobnin-zabbix-datasource",
            "uid": "${DS_ZABBIX}"
          },
          "functions": [],
          "group": {
            "filter": "HomeServer/pysical-host"
          },
          "host": {
            "filter": "/ray-hapve0.*/"
          },
          "item": {
            "filter": "Proxmox: Storage [ray-hapve03/qnap-haproxmox-backup]: Size"
          },
          "itemTag": {
            "filter": ""
          },
          "macro": {
            "filter": ""
          },
          "options": {
            "count": false,
            "disableDataAlignment": false,
            "showDisabledItems": false,
            "skipEmptyValues": false,
            "useTrends": "default",
            "useZabbixValueMapping": false
          },
          "proxy": {
            "filter": ""
          },
          "queryType": "0",
          "refId": "A",
          "resultFormat": "time_series",
          "schema": 12,
          "table": {
            "skipEmptyValues": false
          },
          "tags": {
            "filter": ""
          },
          "textFilter": "",
          "trigger": {
            "filter": ""
          }
        }
      ],
      "title": "QNAP Storage",
      "transformations": [],
      "type": "stat"
    },
    {
      "datasource": {
        "type": "alexanderzobnin-zabbix-datasource",
        "uid": "${DS_ZABBIX}"
      },
      "fieldConfig": {
        "defaults": {
          "color": {
            "mode": "palette-classic"
          },
          "custom": {
            "axisCenteredZero": false,
            "axisColorMode": "text",
            "axisLabel": "",
            "axisPlacement": "auto",
            "barAlignment": 0,
            "drawStyle": "line",
            "fillOpacity": 0,
            "gradientMode": "none",
            "hideFrom": {
              "legend": false,
              "tooltip": false,
              "viz": false
            },
            "lineInterpolation": "linear",
            "lineWidth": 1,
            "pointSize": 5,
            "scaleDistribution": {
              "type": "linear"
            },
            "showPoints": "auto",
            "spanNulls": false,
            "stacking": {
              "group": "A",
              "mode": "none"
            },
            "thresholdsStyle": {
              "mode": "off"
            }
          },
          "mappings": [],
          "thresholds": {
            "mode": "absolute",
            "steps": [
              {
                "color": "green",
                "value": null
              }
            ]
          },
          "unit": "bytes"
        },
        "overrides": []
      },
      "gridPos": {
        "h": 10,
        "w": 12,
        "x": 0,
        "y": 4
      },
      "id": 109,
      "options": {
        "legend": {
          "calcs": [
            "last"
          ],
          "displayMode": "table",
          "placement": "bottom",
          "showLegend": true
        },
        "tooltip": {
          "mode": "single",
          "sort": "none"
        }
      },
      "pluginVersion": "9.1.0",
      "targets": [
        {
          "application": {
            "filter": ""
          },
          "countTriggersBy": "",
          "datasource": {
            "type": "alexanderzobnin-zabbix-datasource",
            "uid": "${DS_ZABBIX}"
          },
          "functions": [],
          "group": {
            "filter": "HomeServer/pysical-host"
          },
          "host": {
            "filter": "/ray-hapve0.*/"
          },
          "item": {
            "filter": "CPU utilization"
          },
          "itemTag": {
            "filter": ""
          },
          "macro": {
            "filter": ""
          },
          "options": {
            "count": false,
            "disableDataAlignment": false,
            "showDisabledItems": false,
            "skipEmptyValues": false,
            "useTrends": "default",
            "useZabbixValueMapping": false
          },
          "proxy": {
            "filter": ""
          },
          "queryType": "0",
          "refId": "A",
          "resultFormat": "time_series",
          "schema": 12,
          "table": {
            "skipEmptyValues": false
          },
          "tags": {
            "filter": ""
          },
          "textFilter": "",
          "trigger": {
            "filter": ""
          }
        }
      ],
      "title": "CPU utilization",
      "transformations": [],
      "type": "timeseries"
    },
    {
      "datasource": {
        "type": "alexanderzobnin-zabbix-datasource",
        "uid": "${DS_ZABBIX}"
      },
      "fieldConfig": {
        "defaults": {
          "color": {
            "mode": "palette-classic"
          },
          "custom": {
            "axisCenteredZero": false,
            "axisColorMode": "text",
            "axisLabel": "",
            "axisPlacement": "auto",
            "barAlignment": 0,
            "drawStyle": "line",
            "fillOpacity": 0,
            "gradientMode": "none",
            "hideFrom": {
              "legend": false,
              "tooltip": false,
              "viz": false
            },
            "lineInterpolation": "linear",
            "lineWidth": 1,
            "pointSize": 5,
            "scaleDistribution": {
              "type": "linear"
            },
            "showPoints": "auto",
            "spanNulls": false,
            "stacking": {
              "group": "A",
              "mode": "none"
            },
            "thresholdsStyle": {
              "mode": "off"
            }
          },
          "mappings": [],
          "thresholds": {
            "mode": "absolute",
            "steps": [
              {
                "color": "green",
                "value": null
              }
            ]
          },
          "unit": "bytes"
        },
        "overrides": []
      },
      "gridPos": {
        "h": 10,
        "w": 12,
        "x": 12,
        "y": 4
      },
      "id": 114,
      "options": {
        "legend": {
          "calcs": [
            "last"
          ],
          "displayMode": "table",
          "placement": "bottom",
          "showLegend": true
        },
        "tooltip": {
          "mode": "single",
          "sort": "none"
        }
      },
      "pluginVersion": "9.1.0",
      "targets": [
        {
          "application": {
            "filter": ""
          },
          "countTriggersBy": "",
          "datasource": {
            "type": "alexanderzobnin-zabbix-datasource",
            "uid": "${DS_ZABBIX}"
          },
          "functions": [],
          "group": {
            "filter": "HomeServer/pysical-host"
          },
          "host": {
            "filter": "/ray-hapve0.*/"
          },
          "item": {
            "filter": "CPU iowait time"
          },
          "itemTag": {
            "filter": ""
          },
          "macro": {
            "filter": ""
          },
          "options": {
            "count": false,
            "disableDataAlignment": false,
            "showDisabledItems": false,
            "skipEmptyValues": false,
            "useTrends": "default",
            "useZabbixValueMapping": false
          },
          "proxy": {
            "filter": ""
          },
          "queryType": "0",
          "refId": "A",
          "resultFormat": "time_series",
          "schema": 12,
          "table": {
            "skipEmptyValues": false
          },
          "tags": {
            "filter": ""
          },
          "textFilter": "",
          "trigger": {
            "filter": ""
          }
        }
      ],
      "title": "CPU I/O",
      "transformations": [],
      "type": "timeseries"
    },
    {
      "datasource": {
        "type": "alexanderzobnin-zabbix-datasource",
        "uid": "${DS_ZABBIX}"
      },
      "fieldConfig": {
        "defaults": {
          "color": {
            "mode": "palette-classic"
          },
          "custom": {
            "axisCenteredZero": false,
            "axisColorMode": "text",
            "axisLabel": "",
            "axisPlacement": "auto",
            "barAlignment": 0,
            "drawStyle": "line",
            "fillOpacity": 0,
            "gradientMode": "none",
            "hideFrom": {
              "legend": false,
              "tooltip": false,
              "viz": false
            },
            "lineInterpolation": "linear",
            "lineWidth": 1,
            "pointSize": 5,
            "scaleDistribution": {
              "type": "linear"
            },
            "showPoints": "auto",
            "spanNulls": false,
            "stacking": {
              "group": "A",
              "mode": "none"
            },
            "thresholdsStyle": {
              "mode": "off"
            }
          },
          "mappings": [],
          "thresholds": {
            "mode": "absolute",
            "steps": [
              {
                "color": "green",
                "value": null
              }
            ]
          },
          "unit": "bytes"
        },
        "overrides": []
      },
      "gridPos": {
        "h": 10,
        "w": 12,
        "x": 0,
        "y": 14
      },
      "id": 108,
      "options": {
        "legend": {
          "calcs": [
            "last"
          ],
          "displayMode": "table",
          "placement": "bottom",
          "showLegend": true
        },
        "tooltip": {
          "mode": "single",
          "sort": "none"
        }
      },
      "pluginVersion": "9.1.0",
      "targets": [
        {
          "application": {
            "filter": ""
          },
          "countTriggersBy": "",
          "datasource": {
            "type": "alexanderzobnin-zabbix-datasource",
            "uid": "${DS_ZABBIX}"
          },
          "functions": [],
          "group": {
            "filter": "HomeServer/pysical-host"
          },
          "host": {
            "filter": "/ray-hapve0.*/"
          },
          "item": {
            "filter": "Memory utilization"
          },
          "itemTag": {
            "filter": ""
          },
          "macro": {
            "filter": ""
          },
          "options": {
            "count": false,
            "disableDataAlignment": false,
            "showDisabledItems": false,
            "skipEmptyValues": false,
            "useTrends": "default",
            "useZabbixValueMapping": false
          },
          "proxy": {
            "filter": ""
          },
          "queryType": "0",
          "refId": "A",
          "resultFormat": "time_series",
          "schema": 12,
          "table": {
            "skipEmptyValues": false
          },
          "tags": {
            "filter": ""
          },
          "textFilter": "",
          "trigger": {
            "filter": ""
          }
        }
      ],
      "title": "Memory utilization",
      "transformations": [],
      "type": "timeseries"
    },
    {
      "datasource": {
        "type": "alexanderzobnin-zabbix-datasource",
        "uid": "${DS_ZABBIX}"
      },
      "fieldConfig": {
        "defaults": {
          "color": {
            "mode": "palette-classic"
          },
          "custom": {
            "axisCenteredZero": false,
            "axisColorMode": "text",
            "axisLabel": "",
            "axisPlacement": "auto",
            "barAlignment": 0,
            "drawStyle": "line",
            "fillOpacity": 0,
            "gradientMode": "none",
            "hideFrom": {
              "legend": false,
              "tooltip": false,
              "viz": false
            },
            "lineInterpolation": "linear",
            "lineWidth": 1,
            "pointSize": 5,
            "scaleDistribution": {
              "type": "linear"
            },
            "showPoints": "auto",
            "spanNulls": false,
            "stacking": {
              "group": "A",
              "mode": "none"
            },
            "thresholdsStyle": {
              "mode": "off"
            }
          },
          "mappings": [],
          "thresholds": {
            "mode": "absolute",
            "steps": [
              {
                "color": "green",
                "value": null
              }
            ]
          },
          "unit": "bytes"
        },
        "overrides": []
      },
      "gridPos": {
        "h": 10,
        "w": 12,
        "x": 12,
        "y": 14
      },
      "id": 113,
      "options": {
        "legend": {
          "calcs": [
            "last"
          ],
          "displayMode": "table",
          "placement": "bottom",
          "showLegend": true
        },
        "tooltip": {
          "mode": "single",
          "sort": "none"
        }
      },
      "pluginVersion": "9.1.0",
      "targets": [
        {
          "application": {
            "filter": ""
          },
          "countTriggersBy": "",
          "datasource": {
            "type": "alexanderzobnin-zabbix-datasource",
            "uid": "${DS_ZABBIX}"
          },
          "functions": [],
          "group": {
            "filter": "HomeServer/pysical-host"
          },
          "host": {
            "filter": "/ray-hapve0.*/"
          },
          "item": {
            "filter": "Proxmox: Storage [ray-hapve01/qnap-haproxmox-backup]: Used"
          },
          "itemTag": {
            "filter": ""
          },
          "macro": {
            "filter": ""
          },
          "options": {
            "count": false,
            "disableDataAlignment": false,
            "showDisabledItems": false,
            "skipEmptyValues": false,
            "useTrends": "default",
            "useZabbixValueMapping": false
          },
          "proxy": {
            "filter": ""
          },
          "queryType": "0",
          "refId": "A",
          "resultFormat": "time_series",
          "schema": 12,
          "table": {
            "skipEmptyValues": false
          },
          "tags": {
            "filter": ""
          },
          "textFilter": "",
          "trigger": {
            "filter": ""
          }
        },
        {
          "application": {
            "filter": ""
          },
          "countTriggersBy": "",
          "datasource": {
            "type": "alexanderzobnin-zabbix-datasource",
            "uid": "${DS_ZABBIX}"
          },
          "functions": [],
          "group": {
            "filter": "HomeServer/pysical-host"
          },
          "hide": false,
          "host": {
            "filter": "/ray-hapve0.*/"
          },
          "item": {
            "filter": "Proxmox: Storage [ray-hapve01/synology-haproxmox]: Used"
          },
          "itemTag": {
            "filter": ""
          },
          "macro": {
            "filter": ""
          },
          "options": {
            "count": false,
            "disableDataAlignment": false,
            "showDisabledItems": false,
            "skipEmptyValues": false,
            "useTrends": "default",
            "useZabbixValueMapping": false
          },
          "proxy": {
            "filter": ""
          },
          "queryType": "0",
          "refId": "B",
          "resultFormat": "time_series",
          "schema": 12,
          "table": {
            "skipEmptyValues": false
          },
          "tags": {
            "filter": ""
          },
          "textFilter": "",
          "trigger": {
            "filter": ""
          }
        }
      ],
      "title": "Stogate utilization",
      "transformations": [],
      "type": "timeseries"
    },
    {
      "datasource": {
        "type": "alexanderzobnin-zabbix-datasource",
        "uid": "${DS_ZABBIX}"
      },
      "fieldConfig": {
        "defaults": {
          "color": {
            "mode": "thresholds"
          },
          "custom": {
            "align": "center",
            "displayMode": "color-text",
            "filterable": true,
            "inspect": true
          },
          "mappings": [
            {
              "options": {
                "1": {
                  "index": 0,
                  "text": "ONLINE"
                }
              },
              "type": "value"
            }
          ],
          "thresholds": {
            "mode": "absolute",
            "steps": [
              {
                "color": "green",
                "value": null
              }
            ]
          }
        },
        "overrides": []
      },
      "gridPos": {
        "h": 9,
        "w": 24,
        "x": 0,
        "y": 24
      },
      "id": 106,
      "options": {
        "footer": {
          "fields": "",
          "reducer": [
            "sum"
          ],
          "show": false
        },
        "showHeader": true,
        "sortBy": [
          {
            "desc": true,
            "displayName": "Time"
          }
        ]
      },
      "pluginVersion": "9.1.0",
      "targets": [
        {
          "application": {
            "filter": ""
          },
          "countTriggersBy": "",
          "datasource": {
            "type": "alexanderzobnin-zabbix-datasource",
            "uid": "${DS_ZABBIX}"
          },
          "functions": [],
          "group": {
            "filter": "HomeServer/pysical-host"
          },
          "host": {
            "filter": "/ray-hapve01/"
          },
          "item": {
            "filter": "Proxmox: Node [ray-hapve01]: Status"
          },
          "itemTag": {
            "filter": ""
          },
          "macro": {
            "filter": ""
          },
          "options": {
            "count": false,
            "disableDataAlignment": false,
            "showDisabledItems": false,
            "skipEmptyValues": false,
            "useTrends": "default",
            "useZabbixValueMapping": false
          },
          "proxy": {
            "filter": ""
          },
          "queryType": "0",
          "refId": "A",
          "resultFormat": "time_series",
          "schema": 12,
          "table": {
            "skipEmptyValues": false
          },
          "tags": {
            "filter": ""
          },
          "textFilter": "",
          "trigger": {
            "filter": ""
          }
        },
        {
          "application": {
            "filter": ""
          },
          "countTriggersBy": "",
          "datasource": {
            "type": "alexanderzobnin-zabbix-datasource",
            "uid": "${DS_ZABBIX}"
          },
          "functions": [],
          "group": {
            "filter": "HomeServer/pysical-host"
          },
          "hide": false,
          "host": {
            "filter": "/ray-hapve01/"
          },
          "item": {
            "filter": "Proxmox: Node [ray-hapve02]: Status"
          },
          "itemTag": {
            "filter": ""
          },
          "macro": {
            "filter": ""
          },
          "options": {
            "count": false,
            "disableDataAlignment": false,
            "showDisabledItems": false,
            "skipEmptyValues": false,
            "useTrends": "default",
            "useZabbixValueMapping": false
          },
          "proxy": {
            "filter": ""
          },
          "queryType": "0",
          "refId": "B",
          "resultFormat": "time_series",
          "schema": 12,
          "table": {
            "skipEmptyValues": false
          },
          "tags": {
            "filter": ""
          },
          "textFilter": "",
          "trigger": {
            "filter": ""
          }
        },
        {
          "application": {
            "filter": ""
          },
          "countTriggersBy": "",
          "datasource": {
            "type": "alexanderzobnin-zabbix-datasource",
            "uid": "${DS_ZABBIX}"
          },
          "functions": [],
          "group": {
            "filter": "HomeServer/pysical-host"
          },
          "hide": false,
          "host": {
            "filter": "/ray-hapve01/"
          },
          "item": {
            "filter": "Proxmox: Node [ray-hapve03]: Status"
          },
          "itemTag": {
            "filter": ""
          },
          "macro": {
            "filter": ""
          },
          "options": {
            "count": false,
            "disableDataAlignment": false,
            "showDisabledItems": false,
            "skipEmptyValues": false,
            "useTrends": "default",
            "useZabbixValueMapping": false
          },
          "proxy": {
            "filter": ""
          },
          "queryType": "0",
          "refId": "C",
          "resultFormat": "time_series",
          "schema": 12,
          "table": {
            "skipEmptyValues": false
          },
          "tags": {
            "filter": ""
          },
          "textFilter": "",
          "trigger": {
            "filter": ""
          }
        },
        {
          "application": {
            "filter": ""
          },
          "countTriggersBy": "",
          "datasource": {
            "type": "alexanderzobnin-zabbix-datasource",
            "uid": "${DS_ZABBIX}"
          },
          "functions": [],
          "group": {
            "filter": "HomeServer/pysical-host"
          },
          "hide": false,
          "host": {
            "filter": "/ray-hapve01/"
          },
          "item": {
            "filter": "Proxmox: Node [ray-hapve04]: Status"
          },
          "itemTag": {
            "filter": ""
          },
          "macro": {
            "filter": ""
          },
          "options": {
            "count": false,
            "disableDataAlignment": false,
            "showDisabledItems": false,
            "skipEmptyValues": false,
            "useTrends": "default",
            "useZabbixValueMapping": false
          },
          "proxy": {
            "filter": ""
          },
          "queryType": "0",
          "refId": "D",
          "resultFormat": "time_series",
          "schema": 12,
          "table": {
            "skipEmptyValues": false
          },
          "tags": {
            "filter": ""
          },
          "textFilter": "",
          "trigger": {
            "filter": ""
          }
        }
      ],
      "title": "Proxmox Status",
      "transformations": [],
      "type": "table"
    }
  ],
  "refresh": "5s",
  "schemaVersion": 37,
  "style": "dark",
  "tags": [],
  "templating": {
    "list": []
  },
  "time": {
    "from": "now-12h",
    "to": "now"
  },
  "timepicker": {
    "refresh_intervals": [
      "5s",
      "10s",
      "30s",
      "1m",
      "5m",
      "15m",
      "30m",
      "1h",
      "2h",
      "1d"
    ],
    "time_options": [
      "5m",
      "15m",
      "1h",
      "6h",
      "12h",
      "24h",
      "2d",
      "7d",
      "30d"
    ]
  },
  "timezone": "",
  "title": "proxmox stats",
  "uid": "PWwfCiE4k",
  "version": 9,
  "weekStart": ""
}